odoo10_addon_account_invoice_overdue_warn_sale-10.0.1.0.0.99.dev2-py3.8-nspkg.pth
odoo/addons/account_invoice_overdue_warn_sale/README.rst
odoo/addons/account_invoice_overdue_warn_sale/__init__.py
odoo/addons/account_invoice_overdue_warn_sale/__manifest__.py
odoo/addons/account_invoice_overdue_warn_sale/i18n/account_invoice_overdue_warn_sale.pot
odoo/addons/account_invoice_overdue_warn_sale/i18n/fr.po
odoo/addons/account_invoice_overdue_warn_sale/models/__init__.py
odoo/addons/account_invoice_overdue_warn_sale/models/sale_order.py
odoo/addons/account_invoice_overdue_warn_sale/readme/CONTRIBUTORS.rst
odoo/addons/account_invoice_overdue_warn_sale/readme/DESCRIPTION.rst
odoo/addons/account_invoice_overdue_warn_sale/static/description/icon.png
odoo/addons/account_invoice_overdue_warn_sale/static/description/index.html
odoo/addons/account_invoice_overdue_warn_sale/static/description/sale_order_overdue_invoice_warn.png
odoo/addons/account_invoice_overdue_warn_sale/views/sale_order.xml
odoo10_addon_account_invoice_overdue_warn_sale-10.0.1.0.0.99.dev2.dist-info/METADATA
odoo10_addon_account_invoice_overdue_warn_sale-10.0.1.0.0.99.dev2.dist-info/WHEEL
odoo10_addon_account_invoice_overdue_warn_sale-10.0.1.0.0.99.dev2.dist-info/namespace_packages.txt
odoo10_addon_account_invoice_overdue_warn_sale-10.0.1.0.0.99.dev2.dist-info/top_level.txt
odoo10_addon_account_invoice_overdue_warn_sale-10.0.1.0.0.99.dev2.dist-info/RECORD
